dubina/__init__.py
dubina/demo_client.py
dubina/demo_server.py
dubina/demo_webpage.py
dubina/server_factory.py
dubina/utils.py
dubina/locale/ru.py
dubina/manipulators/sd1/client.py
dubina/manipulators/sd1/protocol.py
dubina/manipulators/sd1/server_handler.py
dubina/remote/client_base.py
dubina/remote/internal_api_server.py
dubina/remote/protocol.py
dubina/remote/server.py
dubina/web/server.py
dubina-1.0.0.dist-info/METADATA
dubina-1.0.0.dist-info/WHEEL
dubina-1.0.0.dist-info/top_level.txt
dubina-1.0.0.dist-info/RECORD
