Metadata-Version: 2.4
Name: dubina
Version: 1.0.0
Summary: Библиотека для управления роботами-манипуляторами с очередью клиентов и веб-интерфейсом.
Author-email: p5ych0p41h <email@email.com>
License: MIT
Classifier: Programming Language :: Python :: 3
Classifier: License :: OSI Approved :: MIT License
Classifier: Operating System :: OS Independent
Requires-Python: >=3.9
Requires-Dist: pyserial
Requires-Dist: colorama
Requires-Dist: Flask
Requires-Dist: Flask-SocketIO
Requires-Dist: eventlet
